k2catalogue/__init__.py
k2catalogue/cli.py
k2catalogue/k2logging.py
k2catalogue/models.py
k2catalogue/proposal_urls.py
k2catalogue/simbad.py
k2catalogue-0.5.0.dist-info/DESCRIPTION.rst
k2catalogue-0.5.0.dist-info/entry_points.txt
k2catalogue-0.5.0.dist-info/METADATA
k2catalogue-0.5.0.dist-info/metadata.json
k2catalogue-0.5.0.dist-info/RECORD
k2catalogue-0.5.0.dist-info/top_level.txt
k2catalogue-0.5.0.dist-info/WHEEL
