Metadata-Version: 2.0
Name: k2catalogue
Version: 0.5.0
Summary: K2 Catalogue Queryier
Home-page: https://github.com/mindriot101/k2catalogue
Author: Simon Walker
Author-email: s.r.walker101@googlemail.com
License: MIT
Keywords: astronomy kepler metadata
Platform: UNKNOWN
Classifier: Development Status :: 3 - Alpha
Classifier: Intended Audience :: Science/Research
Classifier: Topic :: Scientific/Engineering :: Astronomy
Classifier: License :: OSI Approved :: MIT License
Classifier: Programming Language :: Python :: 2
Classifier: Programming Language :: Python :: 2.6
Classifier: Programming Language :: Python :: 2.7
Classifier: Programming Language :: Python :: 3
Classifier: Programming Language :: Python :: 3.2
Classifier: Programming Language :: Python :: 3.3
Classifier: Programming Language :: Python :: 3.4
Requires-Dist: requests
Requires-Dist: sqlalchemy
Requires-Dist: ipython
Requires-Dist: vcrpy
Requires-Dist: beautifulsoup4
Requires-Dist: lxml
